solareclipseworkbench/__init__.py
solareclipseworkbench/__main__.py
solareclipseworkbench/besselian_element_generator.py
solareclipseworkbench/camera.py
solareclipseworkbench/commands.py
solareclipseworkbench/de421.bsp
solareclipseworkbench/deltat.csv
solareclipseworkbench/eclipse_besselian.csv
solareclipseworkbench/example_scripts/20240408.txt
solareclipseworkbench/example_scripts/20250329.txt
solareclipseworkbench/example_scripts/__init__.py
solareclipseworkbench/example_scripts/test.txt
solareclipseworkbench/example_scripts/testEOS1000D.txt
solareclipseworkbench/example_scripts/testEOS80D.txt
solareclipseworkbench/example_scripts/testEOSR.txt
solareclipseworkbench/example_scripts/testNikon.txt
solareclipseworkbench/example_scripts/voice_prompts.txt
solareclipseworkbench/example_scripts/voice_prompts_basic.txt
solareclipseworkbench/gps.py
solareclipseworkbench/gui.py
solareclipseworkbench/img/__init__.py
solareclipseworkbench/img/astrowimsara.jpg
solareclipseworkbench/img/calendar.png
solareclipseworkbench/img/camera.png
solareclipseworkbench/img/clock.png
solareclipseworkbench/img/datetime-format-popup.png
solareclipseworkbench/img/eclipse-date-popup.png
solareclipseworkbench/img/folder.png
solareclipseworkbench/img/location-popup.png
solareclipseworkbench/img/location.png
solareclipseworkbench/img/logo-small.jpg
solareclipseworkbench/img/logo-small.svg
solareclipseworkbench/img/logo.jpg
solareclipseworkbench/img/save.png
solareclipseworkbench/img/settings.png
solareclipseworkbench/img/simulation-popup.png
solareclipseworkbench/img/simulator.png
solareclipseworkbench/img/stop.png
solareclipseworkbench/img/toolbar.png
solareclipseworkbench/img/ui-top.png
solareclipseworkbench/location.py
solareclipseworkbench/notifications.py
solareclipseworkbench/nutation.py
solareclipseworkbench/observer.py
solareclipseworkbench/reference_moments.py
solareclipseworkbench/scripts.py
solareclipseworkbench/sew.py
solareclipseworkbench/solar_eclipse.py
solareclipseworkbench-1.2.4.dist-info/METADATA
solareclipseworkbench-1.2.4.dist-info/WHEEL
solareclipseworkbench-1.2.4.dist-info/licenses/LICENSE
solareclipseworkbench-1.2.4.dist-info/RECORD
