Metadata-Version: 2.4
Name: solareclipseworkbench
Version: 1.2.4
Summary: Tools to photograph solar eclipses
License: GPL-3.0-or-later
License-File: LICENSE
Keywords: astronomy,photography,solar eclipse
Author: Sara Regibo
Author-email: sararegibo@gmail.com
Requires-Python: >=3.11,<4.0
Classifier: License :: OSI Approved :: GNU General Public License v3 or later (GPLv3+)
Classifier: Programming Language :: Python :: 3
Classifier: Programming Language :: Python :: 3.11
Classifier: Programming Language :: Python :: 3.12
Classifier: Programming Language :: Python :: 3.13
Classifier: Programming Language :: Python :: 3.14
Requires-Dist: apscheduler (>=3.10.4,<4.0.0)
Requires-Dist: astropy (>=7.0.0,<8.0.0)
Requires-Dist: geodatasets (>=2023.12.0,<2024.0.0)
Requires-Dist: geopandas (>=0.14.2,<0.15.0)
Requires-Dist: gphoto2 (>=2.6.0,<3.0.0)
Requires-Dist: gpsdclient (>=1.3.2,<2.0.0)
Requires-Dist: jplephem (>=2.21,<3.0)
Requires-Dist: matplotlib (>=3.8.2,<4.0.0)
Requires-Dist: playsound3 (>=3.2.4,<4.0.0)
Requires-Dist: pynmea2 (>=1.19.0,<2.0.0)
Requires-Dist: pyqt6 (>=6.6.1,<7.0.0)
Requires-Dist: pyserial (>=3.5,<4.0)
Requires-Dist: skyfield (>=1.47,<2.0)
Requires-Dist: skyfield-data (>=5.0.0,<6.0.0)
Requires-Dist: timezonefinder (>=6.2.0,<7.0.0)
Project-URL: Repository, https://github.com/AstroWimSara/SolarEclipseWorkbench
